comptools/__init__.py
comptools/_all_classes.py
comptools/abjadtools.py
comptools/advanced_tools.py
comptools/basic_tools.py
comptools/hindemith.py
comptools/kozu.py
comptools/lisparser.py
comptools/master_perms.py
comptools/parsemaker.py
comptools/parsepy.py
comptools/similarity.py
comptools/testam.py
comptools/twelve_tone.py
comptools-1.0.1.dist-info/LICENSE
comptools-1.0.1.dist-info/METADATA
comptools-1.0.1.dist-info/WHEEL
comptools-1.0.1.dist-info/top_level.txt
comptools-1.0.1.dist-info/RECORD
