Metadata-Version: 2.1
Name: comptools
Version: 1.0.1
Summary: Tools for assisting in composing and analyzing music
Home-page: https://github.com/pedrofariacomposer/comptools
Author: peDro faRia
Author-email: pedrofaria1989@gmail.com
Classifier: Programming Language :: Python :: 3
Classifier: License :: OSI Approved :: MIT License
Classifier: Operating System :: OS Independent
Requires-Python: >=3.10
License-File: LICENSE
Requires-Dist: abjad
Requires-Dist: pycse
Requires-Dist: music21
Requires-Dist: numpy
Requires-Dist: matplotlib
Requires-Dist: graphviz
Requires-Dist: sklearn
Requires-Dist: pandas
